MANIFEST.in
README.txt
dev_requirements.txt
requirements.txt
setup.py
test_requirements.txt
version.txt
cloudshell/__init__.py
cloudshell/networking/__init__.py
cloudshell/networking/cisco/__init__.py
cloudshell/networking/cisco/aireos/__init__.py
cloudshell/networking/cisco/aireos/autoload/__init__.py
cloudshell/networking/cisco/aireos/autoload/aireos_autoload.py
cloudshell/networking/cisco/aireos/cli/__init__.py
cloudshell/networking/cisco/aireos/cli/aireos_cli_handler.py
cloudshell/networking/cisco/aireos/cli/aireos_command_modes.py
cloudshell/networking/cisco/aireos/cli/sessions/__init__.py
cloudshell/networking/cisco/aireos/cli/sessions/aireos_ssh_session.py
cloudshell/networking/cisco/aireos/command_actions/__init__.py
cloudshell/networking/cisco/aireos/command_actions/aireos_enbl_disbl_snmp_actions.py
cloudshell/networking/cisco/aireos/command_actions/aireos_firmware_actions.py
cloudshell/networking/cisco/aireos/command_actions/aireos_general_actions.py
cloudshell/networking/cisco/aireos/command_actions/aireos_restore_actions.py
cloudshell/networking/cisco/aireos/command_actions/aireos_save_actions.py
cloudshell/networking/cisco/aireos/command_templates/__init__.py
cloudshell/networking/cisco/aireos/command_templates/aireos_enbl_disbl_snmp.py
cloudshell/networking/cisco/aireos/command_templates/aireos_general_templates.py
cloudshell/networking/cisco/aireos/command_templates/aireos_restore_templates.py
cloudshell/networking/cisco/aireos/command_templates/aireos_save_templates.py
cloudshell/networking/cisco/aireos/exceptions/__init__.py
cloudshell/networking/cisco/aireos/exceptions/aireos_connectivity_error.py
cloudshell/networking/cisco/aireos/flows/__init__.py
cloudshell/networking/cisco/aireos/flows/aireos_autoload_flow.py
cloudshell/networking/cisco/aireos/flows/aireos_disable_snmp_flow.py
cloudshell/networking/cisco/aireos/flows/aireos_enable_snmp_flow.py
cloudshell/networking/cisco/aireos/flows/aireos_load_firmware_flow.py
cloudshell_networking_cisco_aireos.egg-info/PKG-INFO
cloudshell_networking_cisco_aireos.egg-info/SOURCES.txt
cloudshell_networking_cisco_aireos.egg-info/dependency_links.txt
cloudshell_networking_cisco_aireos.egg-info/requires.txt
cloudshell_networking_cisco_aireos.egg-info/top_level.txt
