Metadata-Version: 1.0
Name: cloudshell-networking-cisco-aireos
Version: 2.1.0
Summary: Cisco AireOS wireless controller specific Package
Home-page: http://www.qualisystems.com/
Author: QualiSystems
Author-email: info@qualisystems.com
License: UNKNOWN
Platform: UNKNOWN
